{"nodes": [{"id": "docs_for_educators", "label": "For Educators & Facilitators", "file_type": "document", "source_file": "docs/for-educators.md", "source_location": null, "source_url": null, "captured_at": null, "author": null, "contributor": null}], "edges": [{"source": "docs_for_educators", "target": "docs_user_guide", "relation": "references", "confidence": "EXTRACTED", "confidence_score": 1.0, "source_file": "docs/for-educators.md", "source_location": null, "weight": 1.0}, {"source": "ux_target_audience_elena_vance", "target": "docs_for_educators", "relation": "conceptually_related_to", "confidence": "INFERRED", "confidence_score": 0.85, "source_file": "docs/for-educators.md", "source_location": null, "weight": 0.85}, {"source": "docs_for_educators", "target": "ux_target_audience", "relation": "semantically_similar_to", "confidence": "INFERRED", "confidence_score": 0.75, "source_file": "docs/for-educators.md", "source_location": null, "weight": 0.75}], "hyperedges": []}