{"nodes": [{"id": "h_f_socials_docs_for_educators_md", "label": "for-educators.md", "file_type": "document", "source_file": "docs/for-educators.md", "source_location": "L1"}, {"id": "docs_for_educators_f_socials_for_educators_facilitators", "label": "f-Socials \u2014 For Educators & Facilitators", "file_type": "document", "source_file": "docs/for-educators.md", "source_location": "L1"}, {"id": "docs_for_educators_why_it_works_for_teaching", "label": "Why it works for teaching", "file_type": "document", "source_file": "docs/for-educators.md", "source_location": "L7"}, {"id": "docs_for_educators_a_30_minute_lesson_plan", "label": "A 30-minute lesson plan", "file_type": "document", "source_file": "docs/for-educators.md", "source_location": "L14"}, {"id": "docs_for_educators_discussion_prompts_that_travel", "label": "Discussion prompts that travel", "file_type": "document", "source_file": "docs/for-educators.md", "source_location": "L24"}, {"id": "docs_for_educators_what_to_be_clear_about_with_learners", "label": "What to be clear about with learners", "file_type": "document", "source_file": "docs/for-educators.md", "source_location": "L31"}, {"id": "docs_for_educators_going_further", "label": "Going further", "file_type": "document", "source_file": "docs/for-educators.md", "source_location": "L38"}], "edges": [{"source": "h_f_socials_docs_for_educators_md", "target": "docs_for_educators_f_socials_for_educators_facilitators", "relation": "contains", "confidence": "EXTRACTED", "source_file": "docs/for-educators.md", "source_location": "L1", "weight": 1.0}, {"source": "docs_for_educators_f_socials_for_educators_facilitators", "target": "docs_for_educators_why_it_works_for_teaching", "relation": "contains", "confidence": "EXTRACTED", "source_file": "docs/for-educators.md", "source_location": "L7", "weight": 1.0}, {"source": "docs_for_educators_f_socials_for_educators_facilitators", "target": "docs_for_educators_a_30_minute_lesson_plan", "relation": "contains", "confidence": "EXTRACTED", "source_file": "docs/for-educators.md", "source_location": "L14", "weight": 1.0}, {"source": "h_f_socials_docs_for_educators_md", "target": "h_f_socials_docs_user_guide_md", "relation": "references", "confidence": "EXTRACTED", "source_file": "docs/for-educators.md", "source_location": "L22", "weight": 1.0}, {"source": "docs_for_educators_f_socials_for_educators_facilitators", "target": "docs_for_educators_discussion_prompts_that_travel", "relation": "contains", "confidence": "EXTRACTED", "source_file": "docs/for-educators.md", "source_location": "L24", "weight": 1.0}, {"source": "docs_for_educators_f_socials_for_educators_facilitators", "target": "docs_for_educators_what_to_be_clear_about_with_learners", "relation": "contains", "confidence": "EXTRACTED", "source_file": "docs/for-educators.md", "source_location": "L31", "weight": 1.0}, {"source": "docs_for_educators_f_socials_for_educators_facilitators", "target": "docs_for_educators_going_further", "relation": "contains", "confidence": "EXTRACTED", "source_file": "docs/for-educators.md", "source_location": "L38", "weight": 1.0}], "input_tokens": 0, "output_tokens": 0}